pbskids_dl/__init__.py
pbskids_dl/__main__.py
pbskids_dl/api.py
pbskids_dl-3.3.1.dist-info/METADATA
pbskids_dl-3.3.1.dist-info/WHEEL
pbskids_dl-3.3.1.dist-info/licenses/LICENSE
pbskids_dl-3.3.1.dist-info/RECORD
