Metadata-Version: 2.3
Name: pbskids-dl
Version: 3.3.1
Summary: A downloader for PBS KIDS videos.
Project-URL: Homepage, https://codeberg.org/pbskids-dl/pbskids-dl
Project-URL: Issues, https://codeberg.org/pbskids-dl/pbskids-dl/issues
Maintainer-email: NexusSfan <nexussfan@duck.com>
License: 
License-File: LICENSE
Classifier: Development Status :: 4 - Beta
Classifier: Environment :: Console
Classifier: Environment :: X11 Applications
Classifier: License :: OSI Approved :: Apache Software License
Classifier: Operating System :: OS Independent
Classifier: Programming Language :: Python
Classifier: Programming Language :: Python :: 3
Classifier: Programming Language :: Python :: 3.8
Classifier: Programming Language :: Python :: 3.9
Classifier: Programming Language :: Python :: 3.10
Classifier: Programming Language :: Python :: 3.11
Requires-Python: >=3.8
Requires-Dist: argparse>=1.4.0
Requires-Dist: beautifulsoup4>=4.12.3
Requires-Dist: lxml>=5.2.2
Requires-Dist: urllib3>=2.2.2
